luciusagent/__init__.py
luciusagent/agent.py
luciusagent/lucius_network.coa
luciusagent/lucius_prompt.md
luciusagent/nodes.py
luciusagent-0.2.dist-info/LICENSE
luciusagent-0.2.dist-info/METADATA
luciusagent-0.2.dist-info/WHEEL
luciusagent-0.2.dist-info/top_level.txt
luciusagent-0.2.dist-info/RECORD
